paginate_any/__init__.py
paginate_any/cursor_pagination.py
paginate_any/datastruct.py
paginate_any/exc.py
paginate_any/rest_api.py
paginate_any/ext/__init__.py
paginate_any/ext/fastapi.py
paginate_any/ext/sanic.py
paginate_any/ext/sqlalchemy.py
paginate_any-0.0.2.dist-info/METADATA
paginate_any-0.0.2.dist-info/WHEEL
paginate_any-0.0.2.dist-info/licenses/LICENSE
paginate_any-0.0.2.dist-info/RECORD
