Metadata-Version: 2.1
Name: paginate-any
Version: 0.0.2
Summary: Pagination primitives for any ORM and web-frameworks
Project-URL: Repository, https://github.com/gromsterus/paginate-any
Project-URL: Issues, https://github.com/gromsterus/paginate-any/issues
Author-email: Pavel Gromov <gromsterus@gmail.com>
License:                                  Apache License
License-File: LICENSE
Keywords: cursor,fastapi,orm,pagination,sanic,sqlalchemy,web-framework
Classifier: Development Status :: 4 - Beta
Classifier: Environment :: Web Environment
Classifier: Framework :: AsyncIO
Classifier: Intended Audience :: Developers
Classifier: License :: OSI Approved :: Apache Software License
Classifier: Natural Language :: English
Classifier: Operating System :: OS Independent
Classifier: Programming Language :: Python
Classifier: Programming Language :: Python :: 3
Classifier: Programming Language :: Python :: 3 :: Only
Classifier: Programming Language :: Python :: 3.10
Classifier: Programming Language :: Python :: 3.11
Classifier: Programming Language :: Python :: 3.12
Requires-Python: >=3.10
Requires-Dist: msgspec<1.0,>=0.18.0
Requires-Dist: pybase64<2.0.0,>=1.3.0
Requires-Dist: typing-extensions>=4.0.0
Provides-Extra: dev
Requires-Dist: black==23.12.1; extra == 'dev'
Requires-Dist: mypy==1.8.0; extra == 'dev'
Requires-Dist: pytest-asyncio==0.23.2; extra == 'dev'
Requires-Dist: pytest-cov==4.1.0; extra == 'dev'
Requires-Dist: pytest-mock==3.12.0; extra == 'dev'
Requires-Dist: pytest-randomly==3.15.0; extra == 'dev'
Requires-Dist: pytest==7.4.3; extra == 'dev'
Requires-Dist: ruff==0.1.9; extra == 'dev'
Requires-Dist: types-mock==5.1.0.3; extra == 'dev'
Requires-Dist: types-pyyaml==6.0.12.12; extra == 'dev'
Requires-Dist: types-setuptools==69.0.0.0; extra == 'dev'
Provides-Extra: dev-fastapi
Requires-Dist: fastapi==0.105.0; extra == 'dev-fastapi'
Requires-Dist: httpx==0.26.0; extra == 'dev-fastapi'
Requires-Dist: uvicorn; extra == 'dev-fastapi'
Provides-Extra: dev-sanic
Requires-Dist: sanic-testing==23.6.0; extra == 'dev-sanic'
Requires-Dist: sanic==23.6.0; extra == 'dev-sanic'
Requires-Dist: types-aiofiles==23.2.0.0; extra == 'dev-sanic'
Requires-Dist: types-ujson==5.9.0.0; extra == 'dev-sanic'
Provides-Extra: dev-sqlalchemy
Requires-Dist: aiosqlite<1.0.0,>=0.19.0; extra == 'dev-sqlalchemy'
Requires-Dist: sqlalchemy<3.0.0,>=2.0.0; extra == 'dev-sqlalchemy'
